{
  "meta": {
    "date": "2025-11-21",
    "timestamp": "2025-11-21T10:06:48.695032",
    "subreddits": [
      "wallstreetbets",
      "stocks"
    ],
    "total_posts": 100,
    "total_tickers": 5
  },
  "sentiment_by_ticker": {
    "SPY": {
      "score": 150,
      "mentions": 45,
      "confidence": "high",
      "bullish_keywords": 30,
      "bearish_keywords": 5
    },
    "NVDA": {
      "score": 200,
      "mentions": 60,
      "confidence": "high",
      "bullish_keywords": 50,
      "bearish_keywords": 2
    },
    "GOOGL": {
      "score": -50,
      "mentions": 20,
      "confidence": "medium",
      "bullish_keywords": 5,
      "bearish_keywords": 15
    },
    "TSLA": {
      "score": 0,
      "mentions": 30,
      "confidence": "medium",
      "bullish_keywords": 10,
      "bearish_keywords": 10
    }
  }
}