{
  "last_updated": "2026-01-16T18:32:11.990470+00:00",
  "portfolio": {
    "equity": 4969.32,
    "cash": 4302.08
  },
  "paper_account": {
    "equity": 4969.32,
    "cash": 4302.08,
    "buying_power": 9003.4,
    "total_pl": -30.68000000000029,
    "total_pl_pct": -0.61,
    "positions_count": 8,
    "daily_change": 10.14
  },
  "positions": [
    {
      "symbol": "SPY",
      "qty": 0.576037269,
      "price": 693.075,
      "value": 399.23703,
      "pnl": -0.722969,
      "type": "stock"
    },
    {
      "symbol": "SPY260220P00565000",
      "qty": 1.0,
      "price": 0.46,
      "value": 46.0,
      "pnl": -1.0,
      "type": "option"
    },
    {
      "symbol": "SPY260220P00570000",
      "qty": -1.0,
      "price": 0.5,
      "value": -50.0,
      "pnl": 0.0,
      "type": "option"
    },
    {
      "symbol": "SPY260220P00595000",
      "qty": 1.0,
      "price": 0.72,
      "value": 72.0,
      "pnl": -1.0,
      "type": "option"
    },
    {
      "symbol": "SPY260220P00600000",
      "qty": -1.0,
      "price": 0.8,
      "value": -80.0,
      "pnl": -2.0,
      "type": "option"
    },
    {
      "symbol": "SPY260220P00653000",
      "qty": 1.0,
      "price": 2.63,
      "value": 263.0,
      "pnl": -16.0,
      "type": "option"
    },
    {
      "symbol": "SPY260220P00658000",
      "qty": -1.0,
      "price": 3.06,
      "value": -306.0,
      "pnl": 15.0,
      "type": "option"
    },
    {
      "symbol": "SPY260220P00660000",
      "qty": 1.0,
      "price": 3.23,
      "value": 323.0,
      "pnl": 16.0,
      "type": "option"
    }
  ],
  "trades": {
    "last_trade_date": "2026-01-16",
    "today_trades": 0,
    "total_trades_today": 0,
    "last_trade_symbol": "SPY"
  },
  "risk": {
    "status": "WARNING - NEGATIVE P/L",
    "total_pl": -30.68000000000029,
    "unrealized_pl": 10.277031000000001
  },
  "account": {
    "current_equity": 4969.32,
    "total_pl": -30.68000000000029,
    "total_pl_pct": -0.61,
    "positions_count": 8
  },
  "meta": {
    "last_updated": "2026-01-16T18:32:11.990487+00:00",
    "trade_sync": "alpaca_api",
    "sync_frequency_minutes": 5
  }
}